stakion/__init__.py
stakion/logger.py
stakion/publishers.py
stakion/version.py
stakion_logger-0.0.16.dist-info/LICENSE
stakion_logger-0.0.16.dist-info/METADATA
stakion_logger-0.0.16.dist-info/WHEEL
stakion_logger-0.0.16.dist-info/top_level.txt
stakion_logger-0.0.16.dist-info/RECORD
