Metadata-Version: 2.1
Name: stakion-logger
Version: 0.0.16
Summary: Logger for stakion.
Home-page: https://stakion.io/
Author: Jacques Verre
Author-email: jacques.verre@stackion.io
License: LICENSE.txt
Platform: UNKNOWN
Requires-Python: >=2.7,!=3.0.*,!=3.1.*,!=3.2.*,!=3.3.*
Requires-Dist: requests-futures
Requires-Dist: python-socketio
